[
null,
{"id":1,"expanded":true,"name":"1-0","order":1,"parentId":0,"scrollX":850,"scrollY":1760},
{"id":2,"expanded":true,"name":"1-1","order":3,"parentId":0,"scrollX":1545,"scrollY":3328.5},
{"id":3,"expanded":false,"name":"1-1Room","order":6,"parentId":2,"scrollX":816,"scrollY":640},
{"id":4,"expanded":true,"name":"1-1Underground","order":4,"parentId":2,"scrollX":816,"scrollY":800},
{"id":5,"expanded":true,"name":"1-2","order":10,"parentId":0,"scrollX":1545,"scrollY":1233},
{"id":6,"expanded":false,"name":"1-1UndergroundsUnderground","order":5,"parentId":4,"scrollX":3504,"scrollY":2324},
{"id":7,"expanded":true,"name":"1-1To1-2","order":7,"parentId":2,"scrollX":1569,"scrollY":991.5},
{"id":8,"expanded":false,"name":"Speed","order":9,"parentId":2,"scrollX":3978,"scrollY":396.59999999999997},
{"id":9,"expanded":false,"name":"1-1Boss","order":8,"parentId":7,"scrollX":832,"scrollY":640},
{"id":10,"expanded":false,"name":"废墟民居","order":2,"parentId":1,"scrollX":627.6,"scrollY":406.2},
{"id":11,"expanded":false,"name":"下水道","order":11,"parentId":5,"scrollX":910.2857142857142,"scrollY":566.5714285714286}
]